MANIFEST.in
README.md
VERSION
setup.cfg
setup.py
dgi/__init__.py
dgi/banco.py
dgi/decoradores.py
dgi/excecoes.py
dgi/info.py
dgi/urls.py
dgi/utils.py
dgi.egg-info/PKG-INFO
dgi.egg-info/SOURCES.txt
dgi.egg-info/dependency_links.txt
dgi.egg-info/requires.txt
dgi.egg-info/top_level.txt
dgi/acesso/__init__.py
dgi/acesso/busca.py
dgi/acesso/facilidade.py
dgi/acesso/utils.py
dgi/catalogo/__init__.py
dgi/catalogo/catalogo.py
dgi/catalogo/utils.py
dgi/servicos/__init__.py
dgi/servicos/linux.py
dgi/servicos/windows.py