Metadata-Version: 2.1
Name: dgi
Version: 0.8.6.2
Summary: Ferramenta para facilitar o acesso aos dados disponibilizados pelo DGI/INPE.
Home-page: https://gitlab.com/labisa/catalogo-de-imagens/dgi-dumps
Author: Laboratório de Instrumentação de Sistemas Aquáticos (LabISA)
Author-email: felipe.carlos@fatec.sp.gov.br
License: UNKNOWN
Keywords: dgi,inpe,ferramenta,facilidade
Platform: UNKNOWN
Classifier: Development Status :: 3 - Alpha
Classifier: Intended Audience :: Science/Research
Classifier: Intended Audience :: Developers
Classifier: Topic :: Software Development :: Libraries :: Python Modules
Classifier: Topic :: Utilities
Classifier: Programming Language :: Python
Classifier: Programming Language :: Python :: 3
